plaitime/__init__.py
plaitime/character_bar.py
plaitime/chat_window.py
plaitime/config_dialog.py
plaitime/data_models.py
plaitime/dummy_llm.py
plaitime/generator.py
plaitime/main.py
plaitime/message_widget.py
plaitime/parser.py
plaitime/util.py
plaitime-0.1.0rc1.dist-info/LICENSE
plaitime-0.1.0rc1.dist-info/METADATA
plaitime-0.1.0rc1.dist-info/WHEEL
plaitime-0.1.0rc1.dist-info/entry_points.txt
plaitime-0.1.0rc1.dist-info/top_level.txt
plaitime-0.1.0rc1.dist-info/RECORD
