Metadata-Version: 2.1
Name: plaitime
Version: 0.1.0rc1
Summary: Chat with local AI assistants or roleplay using ollama
Author-email: Hans Dembinski <hans.dembinski@gmail.com>
License: MIT
Classifier: Operating System :: OS Independent
Classifier: Programming Language :: Python :: 3
Requires-Python: >=3.9
License-File: LICENSE
Requires-Dist: pyside6
Requires-Dist: ollama
Requires-Dist: mistune
Requires-Dist: pydantic
Provides-Extra: test
Requires-Dist: pytest ; extra == 'test'
